TheSwiftProgrammingLanguageZhongwenbanV12/README.md
TheSwiftProgrammingLanguageZhongwenbanV12/__init__.py
TheSwiftProgrammingLanguageZhongwenbanV12/__main__.py
TheSwiftProgrammingLanguageZhongwenbanV12/file.epub
TheSwiftProgrammingLanguageZhongwenbanV12/index.html
TheSwiftProgrammingLanguageZhongwenbanV12/css/__init__.py
TheSwiftProgrammingLanguageZhongwenbanV12/css/annotations.css
TheSwiftProgrammingLanguageZhongwenbanV12/css/main.css
TheSwiftProgrammingLanguageZhongwenbanV12/css/normalize.css
TheSwiftProgrammingLanguageZhongwenbanV12/css/popup.css
TheSwiftProgrammingLanguageZhongwenbanV12/font/__init__.py
TheSwiftProgrammingLanguageZhongwenbanV12/font/fontello.eot
TheSwiftProgrammingLanguageZhongwenbanV12/font/fontello.svg
TheSwiftProgrammingLanguageZhongwenbanV12/font/fontello.ttf
TheSwiftProgrammingLanguageZhongwenbanV12/font/fontello.woff
TheSwiftProgrammingLanguageZhongwenbanV12/img/__init__.py
TheSwiftProgrammingLanguageZhongwenbanV12/img/annotator-glyph-sprite.png
TheSwiftProgrammingLanguageZhongwenbanV12/img/annotator-icon-sprite.png
TheSwiftProgrammingLanguageZhongwenbanV12/img/apple-touch-icon.png
TheSwiftProgrammingLanguageZhongwenbanV12/img/cancelfullscreen.png
TheSwiftProgrammingLanguageZhongwenbanV12/img/close.png
TheSwiftProgrammingLanguageZhongwenbanV12/img/fullscreen.png
TheSwiftProgrammingLanguageZhongwenbanV12/img/loader.gif
TheSwiftProgrammingLanguageZhongwenbanV12/img/menu-icon.png
TheSwiftProgrammingLanguageZhongwenbanV12/img/save.png
TheSwiftProgrammingLanguageZhongwenbanV12/img/saved.png
TheSwiftProgrammingLanguageZhongwenbanV12/img/settings-s.png
TheSwiftProgrammingLanguageZhongwenbanV12/img/settings.png
TheSwiftProgrammingLanguageZhongwenbanV12/img/star.png
TheSwiftProgrammingLanguageZhongwenbanV12/js/__init__.py
TheSwiftProgrammingLanguageZhongwenbanV12/js/epub.js
TheSwiftProgrammingLanguageZhongwenbanV12/js/epub.min.js
TheSwiftProgrammingLanguageZhongwenbanV12/js/epub.min.map
TheSwiftProgrammingLanguageZhongwenbanV12/js/hooks.min.js
the_swift_programming_language_zhongwenban_v1_2-2024.3.2.0.dist-info/METADATA
the_swift_programming_language_zhongwenban_v1_2-2024.3.2.0.dist-info/WHEEL
the_swift_programming_language_zhongwenban_v1_2-2024.3.2.0.dist-info/entry_points.txt
the_swift_programming_language_zhongwenban_v1_2-2024.3.2.0.dist-info/top_level.txt
the_swift_programming_language_zhongwenban_v1_2-2024.3.2.0.dist-info/RECORD
